stemmsk-0.0.2.dist-info/entry_points.txt
stemmsk-0.0.2.dist-info/DESCRIPTION.rst
stemmsk-0.0.2.dist-info/WHEEL
stemmsk-0.0.2.dist-info/METADATA
stemmsk-0.0.2.dist-info/RECORD
stemmsk-0.0.2.dist-info/metadata.json
stemmsk-0.0.2.dist-info/top_level.txt
stemmsk/__init__.py
